{
  "_onto_asset": {
    "pulled_at": "2026-06-10T07:37:15.317Z",
    "path": "D:\\GitHub\\dazi-work\\项目\\潘达工程-商务成本\\本体\\onto-assets\\objects\\oot_9ecaf0f498404929.json"
  },
  "id": "oot_9ecaf0f498404929",
  "code": "Company",
  "name": "分公司",
  "description": "分公司/子公司主数据",
  "search_summary": null,
  "search_keywords": null,
  "entity_synonyms_cache": null,
  "object_kind": null,
  "enabled": true,
  "version": 1,
  "properties": [
    {
      "id": "opr_19bd1c245e274d29",
      "code": "code",
      "name": "分公司编码",
      "description": null,
      "value_type": "string",
      "sort_order": 0,
      "extra": null,
      "semantic_role": "dimension",
      "qualified_name": "CompanyCube.company_code",
      "filterable": true,
      "sample_enabled": false,
      "sample_size": 10,
      "sample_cache": null,
      "sample_cache_time": null,
      "sample_cache_ttl": 3600,
      "attribute_synonyms_cache": null
    },
    {
      "id": "opr_0a2f1d8eb80d44bc",
      "code": "id",
      "name": "分公司ID",
      "description": null,
      "value_type": "string",
      "sort_order": 0,
      "extra": null,
      "semantic_role": "dimension",
      "qualified_name": "CompanyCube.company_id",
      "filterable": true,
      "sample_enabled": false,
      "sample_size": 10,
      "sample_cache": null,
      "sample_cache_time": null,
      "sample_cache_ttl": 3600,
      "attribute_synonyms_cache": null
    },
    {
      "id": "opr_6562658868bd4064",
      "code": "name",
      "name": "分公司名称",
      "description": null,
      "value_type": "string",
      "sort_order": 0,
      "extra": null,
      "semantic_role": "dimension",
      "qualified_name": "CompanyCube.company_name",
      "filterable": true,
      "sample_enabled": false,
      "sample_size": 10,
      "sample_cache": null,
      "sample_cache_time": null,
      "sample_cache_ttl": 3600,
      "attribute_synonyms_cache": null
    }
  ],
  "source_bindings": [
    {
      "id": "osb_cb694d9805f74a92",
      "source_kind": "dazi_cube",
      "priority": 0,
      "config": {
        "cube": "CompanyCube"
      }
    }
  ]
}
