{
  "id": 34,
  "flow_id": 112,
  "status": "completed",
  "duration": 5698,
  "node_status": {
    "n-b35f0f30cdf4": {
      "status": "success",
      "node_label": "SQL 销售产品关联",
      "node_uuid": "e31191a4-0588-4a86-bcb7-92eccc1260de",
      "startTime": "2026-06-02T08:51:33.474256Z",
      "endTime": "2026-06-02T08:51:33.521128Z",
      "duration": 46,
      "error": null,
      "traceback": "",
      "output_variable_id": 87,
      "logs": ""
    },
    "n-bed30407bf9d": {
      "status": "success",
      "node_label": "Excel 销售产品提取",
      "node_uuid": "3f151b7f-8c62-4557-89a4-9947a07ad1a7",
      "startTime": "2026-06-02T08:51:33.271130Z",
      "endTime": "2026-06-02T08:51:33.364893Z",
      "duration": 93,
      "error": null,
      "traceback": "",
      "output_variable_id": 85,
      "logs": ""
    },
    "start-node": {
      "status": "success",
      "node_label": "开始",
      "node_uuid": "ebbcc99c-5e50-404d-9784-302071a7db0a",
      "startTime": "2026-06-02T08:51:33.255504Z",
      "endTime": "2026-06-02T08:51:33.255504Z",
      "duration": 0,
      "error": null,
      "traceback": "",
      "output_variable_id": null,
      "logs": ""
    },
    "end-node": {
      "status": "success",
      "node_label": "结束",
      "node_uuid": "c08de2db-7078-4b05-b78c-f22fc793f907",
      "startTime": "2026-06-02T08:51:33.536771Z",
      "endTime": "2026-06-02T08:51:33.555370Z",
      "duration": 18,
      "error": null,
      "traceback": "",
      "output_variable_id": 87,
      "logs": ""
    },
    "n-bbf0b016cb06": {
      "status": "success",
      "node_label": "数据质量检查",
      "node_uuid": "120f11fe-eba1-4ee7-bcea-7bc389634de7",
      "startTime": "2026-06-02T08:51:33.380513Z",
      "endTime": "2026-06-02T08:51:33.458649Z",
      "duration": 78,
      "error": null,
      "traceback": "",
      "output_variable_id": 88,
      "logs": ""
    }
  },
  "execution_logs": [
    {
      "node_id": "start-node",
      "node_label": "开始",
      "status": "success",
      "startTime": "2026-06-02T08:51:33.255504Z",
      "endTime": "2026-06-02T08:51:33.255504Z",
      "duration": 0,
      "error": null,
      "traceback": "",
      "output_variable_id": null,
      "logs": "",
      "step_order": 1,
      "iteration": 0,
      "active_branch": null,
      "execution_id": "e5bc43cb-0713-45f7-838b-9fb007302644"
    },
    {
      "node_id": "n-bed30407bf9d",
      "node_label": "Excel 销售产品提取",
      "status": "success",
      "startTime": "2026-06-02T08:51:33.271130Z",
      "endTime": "2026-06-02T08:51:33.364893Z",
      "duration": 93,
      "error": null,
      "traceback": "",
      "output_variable_id": 85,
      "logs": "",
      "step_order": 2,
      "iteration": 0,
      "active_branch": null,
      "execution_id": "819da706-cd96-4fc5-b860-2c4c033622fc"
    },
    {
      "node_id": "n-bbf0b016cb06",
      "node_label": "数据质量检查",
      "status": "success",
      "startTime": "2026-06-02T08:51:33.380513Z",
      "endTime": "2026-06-02T08:51:33.458649Z",
      "duration": 78,
      "error": null,
      "traceback": "",
      "output_variable_id": 88,
      "logs": "",
      "step_order": 3,
      "iteration": 0,
      "active_branch": null,
      "execution_id": "50956be3-47cc-4e5a-8f03-6776865cba31"
    },
    {
      "node_id": "n-b35f0f30cdf4",
      "node_label": "SQL 销售产品关联",
      "status": "success",
      "startTime": "2026-06-02T08:51:33.474256Z",
      "endTime": "2026-06-02T08:51:33.521128Z",
      "duration": 46,
      "error": null,
      "traceback": "",
      "output_variable_id": 87,
      "logs": "",
      "step_order": 4,
      "iteration": 0,
      "active_branch": null,
      "execution_id": "38ff02fc-ea7f-475d-aab0-37c50a417957"
    },
    {
      "node_id": "end-node",
      "node_label": "结束",
      "status": "success",
      "startTime": "2026-06-02T08:51:33.536771Z",
      "endTime": "2026-06-02T08:51:33.555370Z",
      "duration": 18,
      "error": null,
      "traceback": "",
      "output_variable_id": 87,
      "logs": "",
      "step_order": 5,
      "iteration": 0,
      "active_branch": null,
      "execution_id": "b79cab1a-dc0b-446e-bbe0-0f8943ed76e6"
    }
  ],
  "variables": {
    "V_DQ_SCORE": {
      "id": 89,
      "value": "100",
      "type": "text",
      "node_id": "n-bbf0b016cb06",
      "updated_at": "2026-06-02T07:34:28.320859Z"
    },
    "销售表": {
      "id": 85,
      "value": "uploads/py_result_dc468752-5661-4f52-890f-9fdad1118ae6.parquet",
      "type": "table",
      "node_id": "n-bed30407bf9d",
      "updated_at": "2026-06-02T08:51:33.380513Z"
    },
    "销售产品宽表": {
      "id": 87,
      "value": "uploads/sql_result_67320306-33fb-4721-a8fd-12788f90388d.parquet",
      "type": "table",
      "node_id": "n-b35f0f30cdf4",
      "updated_at": "2026-06-02T08:51:33.521128Z"
    },
    "V_DQ_REPORT": {
      "id": 88,
      "value": "uploads/py_result_2b080141-0e34-45c3-8f36-04f043aba59b.parquet",
      "type": "table",
      "node_id": "n-bbf0b016cb06",
      "updated_at": "2026-06-02T08:51:33.458649Z"
    },
    "产品表": {
      "id": 86,
      "value": "uploads/py_result_f297f14a-42e2-47fc-a4eb-fb2be0599240.parquet",
      "type": "table",
      "node_id": "n-bed30407bf9d",
      "updated_at": "2026-06-02T08:51:33.380513Z"
    }
  },
  "created_at": "2026-06-02T07:16:34.804412Z",
  "completed_at": "2026-06-02T08:51:33.555370Z"
}